oats/__init__.py
oats/printdata.py
oats/printoutput.py
oats/run.py
oats/runcase.py
oats/runfile.py
oats/selecttestcase.py
oats/models/ACLF.py
oats/models/ACOPF.py
oats/models/ACOPF_BM.py
oats/models/DCLF.py
oats/models/DCOPF.py
oats/models/DCOPF_BM.py
oats/models/SCOPF.py
oats/models/SCOPF_BM.py
oats/models/UC.py
oats/models/__init__.py
oats/testcases/__init__.py
oats/testcases/__init__.pyc
oats/testcases/case24_ieee_rts.xlsx
oatspower-0.4.0.dist-info/DESCRIPTION.rst
oatspower-0.4.0.dist-info/METADATA
oatspower-0.4.0.dist-info/RECORD
oatspower-0.4.0.dist-info/WHEEL
oatspower-0.4.0.dist-info/metadata.json
oatspower-0.4.0.dist-info/top_level.txt
