Metadata-Version: 2.0
Name: oatspower
Version: 0.4.0
Summary: OATS: Optimisation and Analysis Toolbox for Power Systems
Home-page: https://github.com/bukhsh/oats
Author: Waqquas Bukhsh
Author-email: wbukhsh@gmail.com
License: GPLv3+
Platform: UNKNOWN
Requires-Dist: pyomo
Requires-Dist: tabulate
Requires-Dist: PyYAML
Requires-Dist: ipython[notebook]
Requires-Dist: openpyxl
Requires-Dist: pymysql
Requires-Dist: pypyodbc
Requires-Dist: pyro4
Requires-Dist: sympy
Requires-Dist: xlrd
Requires-Dist: pandas
